{"cameraMode":{"drawMode":0,"name":"Shaded","section":"Shading Mode"},"sceneLighting":true,"audioPlay":false,"sceneViewState":{"m_AlwaysRefresh":false,"showFog":true,"showSkybox":true,"showFlares":true,"showImageEffects":true,"showParticleSystems":true,"showVisualEffectGraphs":true,"m_FxEnabled":true},"in2DMode":false,"pivot":{"x":-24.03521728515625,"y":22.270496368408204,"z":-12.842811584472657},"rotation":{"x":0.17187650501728059,"y":0.472266286611557,"z":-0.09445436298847199,"w":0.8593645691871643},"size":14.752020835876465,"orthographic":false}